oc-cab-configure.zcml
setup.py
oc_cab.egg-info/PKG-INFO
oc_cab.egg-info/SOURCES.txt
oc_cab.egg-info/dependency_links.txt
oc_cab.egg-info/entry_points.txt
oc_cab.egg-info/namespace_packages.txt
oc_cab.egg-info/not-zip-safe
oc_cab.egg-info/requires.txt
oc_cab.egg-info/top_level.txt
opencore/__init__.py
opencore/cabochon/README.txt
opencore/cabochon/__init__.py
opencore/cabochon/client.py
opencore/cabochon/configure.zcml
opencore/cabochon/interfaces.py
opencore/cabochon/subscribers.py
opencore/cabochon/tests.py
opencore/cabochon/configuration/__init__.py
opencore/cabochon/configuration/setuphandlers.py
opencore/cabochon/testing/__init__.py
opencore/cabochon/testing/utility.py
